mdweek/__init__.py
mdweek/py.typed
mdweek/week.py
mdweek-1.3.0.dist-info/WHEEL
mdweek-1.3.0.dist-info/METADATA
mdweek-1.3.0.dist-info/RECORD
